er_stubs/__init__.py
er_probmodels-0.0.1.dist-info/METADATA
er_probmodels-0.0.1.dist-info/WHEEL
er_probmodels-0.0.1.dist-info/RECORD
