Metadata-Version: 2.1
Name: er_probmodels
Version: 0.0.1
Summary: A stub for the EntityRisk PROVEN probmodels package
Author: EntityRisk, Inc
Author-email: info@entityrisk.com
Requires-Python: >=3.9,<4.0
Classifier: Programming Language :: Python :: 3
Classifier: Programming Language :: Python :: 3.9
Classifier: Programming Language :: Python :: 3.10
Classifier: Programming Language :: Python :: 3.11
Classifier: Programming Language :: Python :: 3.12
